[
{ "directory": "/home/hendrik/Dokumente/Programmieren/C++/Eigene Projekte/Spiele/Space Shooter", "file": "./src/main.cpp", "output": "/tmp/main-4f21ed.o", "arguments": ["/usr/bin/clang++", "-xc++", "./src/main.cpp", "-o", "/tmp/main-4f21ed.o", "--driver-mode=g++", "-std=c++20", "-I", "./include", "-Wall", "-Wextra", "-Wpedantic", "-I", "/home/hendrik/SDL/include/SDL2", "-D", "_REENTRANT", "-L/home/hendrik/SDL/lib", "-Wl,-rpath,/home/hendrik/SDL/lib", "-Wl,--enable-new-dtags", "-lSDL2", "-lSDL2main", "-lSDL2_image", "-lSDL2_mixer", "-lSDL2_ttf", "-ljxl", "-dumpdir", "main-", "--target=x86_64-redhat-linux-gnu"]},
{ "directory": "/home/hendrik/Dokumente/Programmieren/C++/Eigene Projekte/Spiele/Space Shooter", "file": "./src/Game/Configuration.cpp", "output": "/tmp/Configuration-f1fddc.o", "arguments": ["/usr/bin/clang++", "-xc++", "./src/Game/Configuration.cpp", "-o", "/tmp/Configuration-f1fddc.o", "--driver-mode=g++", "-std=c++20", "-I", "./include", "-Wall", "-Wextra", "-Wpedantic", "-I", "/home/hendrik/SDL/include/SDL2", "-D", "_REENTRANT", "-L/home/hendrik/SDL/lib", "-Wl,-rpath,/home/hendrik/SDL/lib", "-Wl,--enable-new-dtags", "-lSDL2", "-lSDL2main", "-lSDL2_image", "-lSDL2_mixer", "-lSDL2_ttf", "-ljxl", "-dumpdir", "main-", "--target=x86_64-redhat-linux-gnu"]},
{ "directory": "/home/hendrik/Dokumente/Programmieren/C++/Eigene Projekte/Spiele/Space Shooter", "file": "./src/Game/EventHandler.cpp", "output": "/tmp/EventHandler-6d1677.o", "arguments": ["/usr/bin/clang++", "-xc++", "./src/Game/EventHandler.cpp", "-o", "/tmp/EventHandler-6d1677.o", "--driver-mode=g++", "-std=c++20", "-I", "./include", "-Wall", "-Wextra", "-Wpedantic", "-I", "/home/hendrik/SDL/include/SDL2", "-D", "_REENTRANT", "-L/home/hendrik/SDL/lib", "-Wl,-rpath,/home/hendrik/SDL/lib", "-Wl,--enable-new-dtags", "-lSDL2", "-lSDL2main", "-lSDL2_image", "-lSDL2_mixer", "-lSDL2_ttf", "-ljxl", "-dumpdir", "main-", "--target=x86_64-redhat-linux-gnu"]},
{ "directory": "/home/hendrik/Dokumente/Programmieren/C++/Eigene Projekte/Spiele/Space Shooter", "file": "./src/Game/Game.cpp", "output": "/tmp/Game-e90f27.o", "arguments": ["/usr/bin/clang++", "-xc++", "./src/Game/Game.cpp", "-o", "/tmp/Game-e90f27.o", "--driver-mode=g++", "-std=c++20", "-I", "./include", "-Wall", "-Wextra", "-Wpedantic", "-I", "/home/hendrik/SDL/include/SDL2", "-D", "_REENTRANT", "-L/home/hendrik/SDL/lib", "-Wl,-rpath,/home/hendrik/SDL/lib", "-Wl,--enable-new-dtags", "-lSDL2", "-lSDL2main", "-lSDL2_image", "-lSDL2_mixer", "-lSDL2_ttf", "-ljxl", "-dumpdir", "main-", "--target=x86_64-redhat-linux-gnu"]},
{ "directory": "/home/hendrik/Dokumente/Programmieren/C++/Eigene Projekte/Spiele/Space Shooter", "file": "./src/Game/objectStorage.cpp", "output": "/tmp/objectStorage-0c003c.o", "arguments": ["/usr/bin/clang++", "-xc++", "./src/Game/objectStorage.cpp", "-o", "/tmp/objectStorage-0c003c.o", "--driver-mode=g++", "-std=c++20", "-I", "./include", "-Wall", "-Wextra", "-Wpedantic", "-I", "/home/hendrik/SDL/include/SDL2", "-D", "_REENTRANT", "-L/home/hendrik/SDL/lib", "-Wl,-rpath,/home/hendrik/SDL/lib", "-Wl,--enable-new-dtags", "-lSDL2", "-lSDL2main", "-lSDL2_image", "-lSDL2_mixer", "-lSDL2_ttf", "-ljxl", "-dumpdir", "main-", "--target=x86_64-redhat-linux-gnu"]},
{ "directory": "/home/hendrik/Dokumente/Programmieren/C++/Eigene Projekte/Spiele/Space Shooter", "file": "./src/Sound/channelControl.cpp", "output": "/tmp/channelControl-6734e8.o", "arguments": ["/usr/bin/clang++", "-xc++", "./src/Sound/channelControl.cpp", "-o", "/tmp/channelControl-6734e8.o", "--driver-mode=g++", "-std=c++20", "-I", "./include", "-Wall", "-Wextra", "-Wpedantic", "-I", "/home/hendrik/SDL/include/SDL2", "-D", "_REENTRANT", "-L/home/hendrik/SDL/lib", "-Wl,-rpath,/home/hendrik/SDL/lib", "-Wl,--enable-new-dtags", "-lSDL2", "-lSDL2main", "-lSDL2_image", "-lSDL2_mixer", "-lSDL2_ttf", "-ljxl", "-dumpdir", "main-", "--target=x86_64-redhat-linux-gnu"]},
{ "directory": "/home/hendrik/Dokumente/Programmieren/C++/Eigene Projekte/Spiele/Space Shooter", "file": "./src/Sound/soundChunk.cpp", "output": "/tmp/soundChunk-df3156.o", "arguments": ["/usr/bin/clang++", "-xc++", "./src/Sound/soundChunk.cpp", "-o", "/tmp/soundChunk-df3156.o", "--driver-mode=g++", "-std=c++20", "-I", "./include", "-Wall", "-Wextra", "-Wpedantic", "-I", "/home/hendrik/SDL/include/SDL2", "-D", "_REENTRANT", "-L/home/hendrik/SDL/lib", "-Wl,-rpath,/home/hendrik/SDL/lib", "-Wl,--enable-new-dtags", "-lSDL2", "-lSDL2main", "-lSDL2_image", "-lSDL2_mixer", "-lSDL2_ttf", "-ljxl", "-dumpdir", "main-", "--target=x86_64-redhat-linux-gnu"]},
{ "directory": "/home/hendrik/Dokumente/Programmieren/C++/Eigene Projekte/Spiele/Space Shooter", "file": "./src/Sound/soundMusic.cpp", "output": "/tmp/soundMusic-a4410b.o", "arguments": ["/usr/bin/clang++", "-xc++", "./src/Sound/soundMusic.cpp", "-o", "/tmp/soundMusic-a4410b.o", "--driver-mode=g++", "-std=c++20", "-I", "./include", "-Wall", "-Wextra", "-Wpedantic", "-I", "/home/hendrik/SDL/include/SDL2", "-D", "_REENTRANT", "-L/home/hendrik/SDL/lib", "-Wl,-rpath,/home/hendrik/SDL/lib", "-Wl,--enable-new-dtags", "-lSDL2", "-lSDL2main", "-lSDL2_image", "-lSDL2_mixer", "-lSDL2_ttf", "-ljxl", "-dumpdir", "main-", "--target=x86_64-redhat-linux-gnu"]},
{ "directory": "/home/hendrik/Dokumente/Programmieren/C++/Eigene Projekte/Spiele/Space Shooter", "file": "./src/Sound/volumeControl.cpp", "output": "/tmp/volumeControl-8a1d13.o", "arguments": ["/usr/bin/clang++", "-xc++", "./src/Sound/volumeControl.cpp", "-o", "/tmp/volumeControl-8a1d13.o", "--driver-mode=g++", "-std=c++20", "-I", "./include", "-Wall", "-Wextra", "-Wpedantic", "-I", "/home/hendrik/SDL/include/SDL2", "-D", "_REENTRANT", "-L/home/hendrik/SDL/lib", "-Wl,-rpath,/home/hendrik/SDL/lib", "-Wl,--enable-new-dtags", "-lSDL2", "-lSDL2main", "-lSDL2_image", "-lSDL2_mixer", "-lSDL2_ttf", "-ljxl", "-dumpdir", "main-", "--target=x86_64-redhat-linux-gnu"]},
{ "directory": "/home/hendrik/Dokumente/Programmieren/C++/Eigene Projekte/Spiele/Space Shooter", "file": "./src/Sprite/AnimatedSprite.cpp", "output": "/tmp/AnimatedSprite-c28819.o", "arguments": ["/usr/bin/clang++", "-xc++", "./src/Sprite/AnimatedSprite.cpp", "-o", "/tmp/AnimatedSprite-c28819.o", "--driver-mode=g++", "-std=c++20", "-I", "./include", "-Wall", "-Wextra", "-Wpedantic", "-I", "/home/hendrik/SDL/include/SDL2", "-D", "_REENTRANT", "-L/home/hendrik/SDL/lib", "-Wl,-rpath,/home/hendrik/SDL/lib", "-Wl,--enable-new-dtags", "-lSDL2", "-lSDL2main", "-lSDL2_image", "-lSDL2_mixer", "-lSDL2_ttf", "-ljxl", "-dumpdir", "main-", "--target=x86_64-redhat-linux-gnu"]},
{ "directory": "/home/hendrik/Dokumente/Programmieren/C++/Eigene Projekte/Spiele/Space Shooter", "file": "./src/Sprite/Asteroid.cpp", "output": "/tmp/Asteroid-1ca7f2.o", "arguments": ["/usr/bin/clang++", "-xc++", "./src/Sprite/Asteroid.cpp", "-o", "/tmp/Asteroid-1ca7f2.o", "--driver-mode=g++", "-std=c++20", "-I", "./include", "-Wall", "-Wextra", "-Wpedantic", "-I", "/home/hendrik/SDL/include/SDL2", "-D", "_REENTRANT", "-L/home/hendrik/SDL/lib", "-Wl,-rpath,/home/hendrik/SDL/lib", "-Wl,--enable-new-dtags", "-lSDL2", "-lSDL2main", "-lSDL2_image", "-lSDL2_mixer", "-lSDL2_ttf", "-ljxl", "-dumpdir", "main-", "--target=x86_64-redhat-linux-gnu"]},
{ "directory": "/home/hendrik/Dokumente/Programmieren/C++/Eigene Projekte/Spiele/Space Shooter", "file": "./src/Sprite/Gem.cpp", "output": "/tmp/Gem-6ae733.o", "arguments": ["/usr/bin/clang++", "-xc++", "./src/Sprite/Gem.cpp", "-o", "/tmp/Gem-6ae733.o", "--driver-mode=g++", "-std=c++20", "-I", "./include", "-Wall", "-Wextra", "-Wpedantic", "-I", "/home/hendrik/SDL/include/SDL2", "-D", "_REENTRANT", "-L/home/hendrik/SDL/lib", "-Wl,-rpath,/home/hendrik/SDL/lib", "-Wl,--enable-new-dtags", "-lSDL2", "-lSDL2main", "-lSDL2_image", "-lSDL2_mixer", "-lSDL2_ttf", "-ljxl", "-dumpdir", "main-", "--target=x86_64-redhat-linux-gnu"]},
{ "directory": "/home/hendrik/Dokumente/Programmieren/C++/Eigene Projekte/Spiele/Space Shooter", "file": "./src/Sprite/IMGSprite.cpp", "output": "/tmp/IMGSprite-b789da.o", "arguments": ["/usr/bin/clang++", "-xc++", "./src/Sprite/IMGSprite.cpp", "-o", "/tmp/IMGSprite-b789da.o", "--driver-mode=g++", "-std=c++20", "-I", "./include", "-Wall", "-Wextra", "-Wpedantic", "-I", "/home/hendrik/SDL/include/SDL2", "-D", "_REENTRANT", "-L/home/hendrik/SDL/lib", "-Wl,-rpath,/home/hendrik/SDL/lib", "-Wl,--enable-new-dtags", "-lSDL2", "-lSDL2main", "-lSDL2_image", "-lSDL2_mixer", "-lSDL2_ttf", "-ljxl", "-dumpdir", "main-", "--target=x86_64-redhat-linux-gnu"]},
{ "directory": "/home/hendrik/Dokumente/Programmieren/C++/Eigene Projekte/Spiele/Space Shooter", "file": "./src/Sprite/Player.cpp", "output": "/tmp/Player-2eb6f3.o", "arguments": ["/usr/bin/clang++", "-xc++", "./src/Sprite/Player.cpp", "-o", "/tmp/Player-2eb6f3.o", "--driver-mode=g++", "-std=c++20", "-I", "./include", "-Wall", "-Wextra", "-Wpedantic", "-I", "/home/hendrik/SDL/include/SDL2", "-D", "_REENTRANT", "-L/home/hendrik/SDL/lib", "-Wl,-rpath,/home/hendrik/SDL/lib", "-Wl,--enable-new-dtags", "-lSDL2", "-lSDL2main", "-lSDL2_image", "-lSDL2_mixer", "-lSDL2_ttf", "-ljxl", "-dumpdir", "main-", "--target=x86_64-redhat-linux-gnu"]},
{ "directory": "/home/hendrik/Dokumente/Programmieren/C++/Eigene Projekte/Spiele/Space Shooter", "file": "./src/Sprite/Sprite.cpp", "output": "/tmp/Sprite-a34675.o", "arguments": ["/usr/bin/clang++", "-xc++", "./src/Sprite/Sprite.cpp", "-o", "/tmp/Sprite-a34675.o", "--driver-mode=g++", "-std=c++20", "-I", "./include", "-Wall", "-Wextra", "-Wpedantic", "-I", "/home/hendrik/SDL/include/SDL2", "-D", "_REENTRANT", "-L/home/hendrik/SDL/lib", "-Wl,-rpath,/home/hendrik/SDL/lib", "-Wl,--enable-new-dtags", "-lSDL2", "-lSDL2main", "-lSDL2_image", "-lSDL2_mixer", "-lSDL2_ttf", "-ljxl", "-dumpdir", "main-", "--target=x86_64-redhat-linux-gnu"]},
{ "directory": "/home/hendrik/Dokumente/Programmieren/C++/Eigene Projekte/Spiele/Space Shooter", "file": "./src/Sprite/Text.cpp", "output": "/tmp/Text-f29540.o", "arguments": ["/usr/bin/clang++", "-xc++", "./src/Sprite/Text.cpp", "-o", "/tmp/Text-f29540.o", "--driver-mode=g++", "-std=c++20", "-I", "./include", "-Wall", "-Wextra", "-Wpedantic", "-I", "/home/hendrik/SDL/include/SDL2", "-D", "_REENTRANT", "-L/home/hendrik/SDL/lib", "-Wl,-rpath,/home/hendrik/SDL/lib", "-Wl,--enable-new-dtags", "-lSDL2", "-lSDL2main", "-lSDL2_image", "-lSDL2_mixer", "-lSDL2_ttf", "-ljxl", "-dumpdir", "main-", "--target=x86_64-redhat-linux-gnu"]},
{ "directory": "/home/hendrik/Dokumente/Programmieren/C++/Eigene Projekte/Spiele/Space Shooter", "file": "./src/Time/Clock.cpp", "output": "/tmp/Clock-3923d3.o", "arguments": ["/usr/bin/clang++", "-xc++", "./src/Time/Clock.cpp", "-o", "/tmp/Clock-3923d3.o", "--driver-mode=g++", "-std=c++20", "-I", "./include", "-Wall", "-Wextra", "-Wpedantic", "-I", "/home/hendrik/SDL/include/SDL2", "-D", "_REENTRANT", "-L/home/hendrik/SDL/lib", "-Wl,-rpath,/home/hendrik/SDL/lib", "-Wl,--enable-new-dtags", "-lSDL2", "-lSDL2main", "-lSDL2_image", "-lSDL2_mixer", "-lSDL2_ttf", "-ljxl", "-dumpdir", "main-", "--target=x86_64-redhat-linux-gnu"]},
{ "directory": "/home/hendrik/Dokumente/Programmieren/C++/Eigene Projekte/Spiele/Space Shooter", "file": "./src/Time/SecondTimer.cpp", "output": "/tmp/SecondTimer-3c2dc3.o", "arguments": ["/usr/bin/clang++", "-xc++", "./src/Time/SecondTimer.cpp", "-o", "/tmp/SecondTimer-3c2dc3.o", "--driver-mode=g++", "-std=c++20", "-I", "./include", "-Wall", "-Wextra", "-Wpedantic", "-I", "/home/hendrik/SDL/include/SDL2", "-D", "_REENTRANT", "-L/home/hendrik/SDL/lib", "-Wl,-rpath,/home/hendrik/SDL/lib", "-Wl,--enable-new-dtags", "-lSDL2", "-lSDL2main", "-lSDL2_image", "-lSDL2_mixer", "-lSDL2_ttf", "-ljxl", "-dumpdir", "main-", "--target=x86_64-redhat-linux-gnu"]}
]
